src/componentes.v
// Banco de registros de dos salidas y una entrada
module regfile(output wire [7:0]  RD1, RD2,     //datos leidos
               input  wire        clk,          // Señal de reloj
               input  wire        we3,          //señal de habilitación de escritura
               input  wire [3:0]  RA1, RA2, WA3,//direcciones de regs leidos y reg a escribir
               input  wire [7:0]  WD3);         //dato a escribir

  reg [7:0] R[0:15]; //memoria de 32 registros de 8 bits de ancho

  initial
  begin
    $readmemb("regfile.dat",R); // inicializa los registros a valores conocidos
  end  
  
  // El registro 0 siempre es cero
  // se leen dos reg combinacionalmente
  // y la escritura del tercero ocurre en flanco de subida del reloj
  always @(posedge clk)
    if (we3) R[WA3] <= WD3;	
  
  assign RD1 = (RA1 != 0) ? R[RA1] : 0;
  assign RD2 = (RA2 != 0) ? R[RA2] : 0;
endmodule


// Sumador simple
module sum(output wire [9:0] Y,     // Salida del sumador
           input  wire [9:0] A, B); // Operandos de la suma

  assign Y = A + B;
endmodule


// Registro de tamaño configurable para modelar el PC. Cambia en cada flanco de subida de reloj o de reset
module registro #(parameter WIDTH = 8)
              (output reg  [WIDTH-1:0] Q,           // Salida del registro
               input  wire             clk, reset,  // Señales de reloj y reseteo
               input  wire [WIDTH-1:0] D);          // Entrada al registro

  always @(posedge clk, posedge reset)
    if (reset) Q <= 0;
    else       Q <= D;
endmodule


// Multiplexor de dos entradas y una salida, de tamaño configurable. Si la señal de selección "s" vale 1, se pone el valor de d1 en la salida; d0 si vale 0
module mux2 #(parameter WIDTH = 8)
             (output wire [WIDTH-1:0] Y,      // Salida del multiplexor
              input  wire [WIDTH-1:0] D0, D1, // Entradas del multiplexor
              input  wire             s);     // Selección

  assign Y = s ? D1 : D0; 
endmodule


//Biestable para el flag de cero
//Biestable tipo D síncrono con reset asíncrono por flanco y entrada de habilitación de carga
module ffd(input wire clk, reset, d, carga, output reg q);
  always @(posedge clk, posedge reset)
    if (reset)
	    q <= 1'b0;
	  else
	    if (carga)
	      q <= d;
endmodule

src/alu.v
module alu(output reg [7:0] S, output reg zero, input wire [7:0] A, B, input wire [2:0] Op);
  always @(A, B, Op)
  begin
    case (Op)              
      3'b000: S = A; 
      3'b001: S = ~A;
      3'b010: S = A + B;
      3'b011: S = A - B;
      3'b100: S = A & B;
      3'b101: S = A | B;
      3'b110: S = -A;
      3'b111: S = -B;
      default: S = 'bx; 
    endcase
    zero = ~(|S);
  end
endmodule

src/memprog.v
module memprog(output wire [15:0] Data,     // Dato que se lee de memoria
               input  wire clk,             // Señal de reloj
               input  wire [9:0] Address);  // Dirección de memoria a la que se accede

  reg [15:0] Mem[0:1023]; //memoria de 1024 palabras de 16 bits de ancho

  initial
  begin
    $readmemb("progfile.dat", Mem); // inicializa la memoria del fichero en texto binario
  end
  assign Data = Mem[Address];
endmodule

src/microc.v
module microc(output wire [5:0] Opcode, output wire z, input wire clk, reset, s_inc, s_inm, we3, wez, input wire [2:0] Op);
//Microcontrolador sin memoria de datos de un solo ciclo

  // Inicialización
  wire [15:0] opcode;
  wire [9:0] mem_dir, pc_dir, sum_result;
  wire [7:0] reg_alu_1, reg_alu_2, wd3, alu_result;
  wire zero; 

  // Obtengo el PC
  registro PC (mem_dir, clk, reset, pc_dir);
  // Obtengo el incremento
  sum suma_pc (sum_result, mem_dir, 10'b0000000001);
  // Obtengo el opcode de la instruccion
  memprog instruccion (opcode, clk, mem_dir);
  // Elijo entre saltar a la direccion o el incremento del PC
  mux2 #(10) mux_10_bit (pc_dir, opcode[9:0], mem_dir, s_inc);

  // Elijo entre el resultado de la alu y la constante inmediata
  mux2 #(8) mux_8_bit (wd3, alu_result, opcode[11:4], s_inm);
  // Hago la operacion correspondiente 
  alu ALU (alu_result, zero, reg_alu_1, reg_alu_2, Op);
  // Proceso el banco de registros
  regfile banco (reg_alu_1, reg_alu_2, clk, we3, opcode[11:8], opcode[7:4], opcode[3:0], wd3);
  // Almaceno en el ffd el zero
  ffd FFZ (clk, reset, zero, wez, z);

  // Asigno los 6 bits más significativos al Opcode
  assign Opcode = opcode[15:10];
endmodule

testbenchs/microc_tb.v
`timescale 1 ns / 10 ps
module microc_tb;

// declaración de variables
  reg test_clk, test_reset, test_s_inc, test_s_inm, test_we3, test_wez;
  reg [2:0] test_Op;
  wire [5:0] test_Opcode;
  wire test_z;
// instanciación del camino de datos
  microc camino(test_Opcode, test_z, test_clk, test_reset, test_s_inc, test_s_inm, test_we3, test_wez, test_Op);

// generación de reloj clk
  always
  begin
    test_clk = 1;
    #10;
    test_clk = 0;
    #10;
  end

// Reseteo y configuración de salidas del testbench
initial
begin
  $dumpfile("data/microc_tb.vcd");
  $dumpvars;
  // ... señal de reset
  test_reset = 1'b1;
  #5;
  test_reset = 1'b0;
end

// jmp: s_inc = 0, we3 = 1 s_inm = x, wez = 1, Op = xxx
// nop: s_inc = 1, we3 = 1, s_inm = x, wez = 1, Op = xxx
// li : s_inc = 1, we3 = 0, s_inm = 1, wez = 1, Op = xxx
// aritmetico-logicas : s_inc = 1, we3 = 1, s_inm = 0, wez = 1, Op = Sí importa pero está dentro de la alu
// jnz : s_inc = 0, we3 = 1, s_inm = x, wez = 0, Op = xxx
// jz : s_inc = 0, we3 = 1, s_inm = x, wez = 0, Op = xxx

// Bloque simulación señales control por ciclo
initial @(posedge test_clk, negedge test_reset)
begin
  #5;
  // retardos y señales para ejecutar primera instrucción (ciclo 1)
  test_s_inc = 1'b0;
  test_we3 = 1'b0;
  test_s_inm = 1'b0; // Don't care
  test_wez = 1'b0;
  test_Op = 3'b000; // Don't care
  #20;
  // retardos y señales para ejecutar primera instrucción (ciclo 1)
  test_s_inc = 1'b1;
  test_we3 = 1'b1;
  test_s_inm = 1'b1; 
  test_wez = 1'b0;
  test_Op = 3'b000; // Don't care
  #20;
  // retardos y señales para ejecutar primera instrucción (ciclo 1)
  test_s_inc = 1'b1;
  test_we3 = 1'b1;
  test_s_inm = 1'b1; 
  test_wez = 1'b0;
  test_Op = 3'b000; // Don't care
  #20;
  // retardos y señales para ejecutar primera instrucción (ciclo 1)
  test_s_inc = 1'b1;
  test_we3 = 1'b1;
  test_s_inm = 1'b1; 
  test_wez = 1'b0;
  test_Op = 3'b000; // Don't care
  #20;
  // retardos y señales para ejecutar primera instrucción (ciclo 1)
  test_s_inc = 1'b1;
  test_we3 = 1'b1;
  test_s_inm = 1'b1; 
  test_wez = 1'b0;
  test_Op = 3'b000; // Don't care
  #20;
  // retardos y señales para ejecutar primera instrucción (ciclo 1)
  test_s_inc = 1'b1;
  test_we3 = 1'b1;
  test_s_inm = 1'b0; // Don't care
  test_wez = 1'b0;
  test_Op = 3'b010; // Add
  #20;
  // retardos y señales para ejecutar primera instrucción (ciclo 1)
  test_s_inc = 1'b1;
  test_we3 = 1'b1;
  test_s_inm = 1'b0; // Don't care
  test_wez = 1'b1;
  test_Op = 3'b011; // Sub
  #20;
  // retardos y señales para ejecutar primera instrucción (ciclo 1)
  test_s_inc = 1'b0;
  test_we3 = 1'b0;
  test_s_inm = 1'b0; // Don't care
  test_wez = 1'b0;
  test_Op = 3'b000; // Don't care
  #20;
  // retardos y señales para ejecutar primera instrucción (ciclo 1)
  test_s_inc = 1'b1;
  test_we3 = 1'b1;
  test_s_inm = 1'b0; // Don't care
  test_wez = 1'b0;
  test_Op = 3'b010; // Add
  #20;
  // retardos y señales para ejecutar primera instrucción (ciclo 1)
  test_s_inc = 1'b1;
  test_we3 = 1'b1;
  test_s_inm = 1'b0; // Don't care
  test_wez = 1'b1;
  test_Op = 3'b011; // Sub
  #20;
  // retardos y señales para ejecutar primera instrucción (ciclo 1)
  test_s_inc = 1'b1;
  test_we3 = 1'b0;
  test_s_inm = 1'b0; // Don't care
  test_wez = 1'b0;
  test_Op = 3'b000; // Don't care
  #20;
  // retardos y señales para ejecutar primera instrucción (ciclo 1)
  test_s_inc = 1'b0;
  test_we3 = 1'b0;
  test_s_inm = 1'b0; // Don't care
  test_wez = 1'b0;
  test_Op = 3'b000; // Don't care
  #20;
  $finish;
end

endmodule

data/microc_tb.vcd
$date
	Fri Nov 15 12:37:54 2024
$end
$version
	Icarus Verilog
$end
$timescale
	10ps
$end
$scope module microc_tb $end
$var wire 1 ! test_z $end
$var wire 6 " test_Opcode [5:0] $end
$var reg 3 # test_Op [2:0] $end
$var reg 1 $ test_clk $end
$var reg 1 % test_reset $end
$var reg 1 & test_s_inc $end
$var reg 1 ' test_s_inm $end
$var reg 1 ( test_we3 $end
$var reg 1 ) test_wez $end
$scope module camino $end
$var wire 3 * Op [2:0] $end
$var wire 1 $ clk $end
$var wire 1 % reset $end
$var wire 1 & s_inc $end
$var wire 1 ' s_inm $end
$var wire 1 ( we3 $end
$var wire 1 ) wez $end
$var wire 1 + zero $end
$var wire 1 ! z $end
$var wire 8 , wd3 [7:0] $end
$var wire 10 - sum_result [9:0] $end
$var wire 8 . reg_alu_2 [7:0] $end
$var wire 8 / reg_alu_1 [7:0] $end
$var wire 10 0 pc_dir [9:0] $end
$var wire 16 1 opcode [15:0] $end
$var wire 10 2 mem_dir [9:0] $end
$var wire 8 3 alu_result [7:0] $end
$var wire 6 4 Opcode [5:0] $end
$scope module ALU $end
$var wire 3 5 Op [2:0] $end
$var wire 8 6 B [7:0] $end
$var wire 8 7 A [7:0] $end
$var reg 8 8 S [7:0] $end
$var reg 1 + zero $end
$upscope $end
$scope module FFZ $end
$var wire 1 ) carga $end
$var wire 1 $ clk $end
$var wire 1 + d $end
$var wire 1 % reset $end
$var reg 1 ! q $end
$upscope $end
$scope module PC $end
$var wire 1 $ clk $end
$var wire 1 % reset $end
$var wire 10 9 D [9:0] $end
$var parameter 32 : WIDTH $end
$var reg 10 ; Q [9:0] $end
$upscope $end
$scope module banco $end
$var wire 4 < RA1 [3:0] $end
$var wire 4 = RA2 [3:0] $end
$var wire 4 > WA3 [3:0] $end
$var wire 1 $ clk $end
$var wire 1 ( we3 $end
$var wire 8 ? WD3 [7:0] $end
$var wire 8 @ RD2 [7:0] $end
$var wire 8 A RD1 [7:0] $end
$upscope $end
$scope module instruccion $end
$var wire 10 B Address [9:0] $end
$var wire 16 C Data [15:0] $end
$var wire 1 $ clk $end
$upscope $end
$scope module mux_10_bit $end
$var wire 10 D D0 [9:0] $end
$var wire 10 E D1 [9:0] $end
$var wire 1 & s $end
$var wire 10 F Y [9:0] $end
$var parameter 32 G WIDTH $end
$upscope $end
$scope module mux_8_bit $end
$var wire 8 H D0 [7:0] $end
$var wire 8 I D1 [7:0] $end
$var wire 1 ' s $end
$var wire 8 J Y [7:0] $end
$var parameter 32 K WIDTH $end
$upscope $end
$scope module suma_pc $end
$var wire 10 L A [9:0] $end
$var wire 10 M B [9:0] $end
$var wire 10 N Y [9:0] $end
$upscope $end
$upscope $end
$upscope $end
$enddefinitions $end
$comment Show the parameter values. $end
$dumpall
b1000 K
b1010 G
b1010 :
$end
#0
$dumpvars
b1 N
b1 M
b0 L
bx J
b0 I
bx H
b0x0x F
b0 E
b101 D
b100000000000101 C
b0 B
b0 A
b0 @
bx ?
b101 >
b0 =
b0 <
b0 ;
b0x0x 9
bx 8
b0 7
b0 6
bx 5
b10000 4
bx 3
b0 2
b100000000000101 1
b0x0x 0
b0 /
b0 .
b1 -
bx ,
x+
bx *
x)
x(
x'
x&
1%
1$
bx #
b10000 "
0!
$end
#1000
0%
#4000
0$
#8000
bx .
bx 6
bx @
bx /
bx 7
bx A
bx "
bx 4
bx >
bx =
bx <
bx I
bx D
bx 1
bx C
bx -
bx N
b0x0x 2
b0x0x ;
b0x0x B
b0x0x E
b0x0x L
bx ,
bx ?
bx J
x+
bx 3
bx 8
bx H
bx 0
bx 9
bx F
b0 #
b0 *
b0 5
1)
0'
1(
0&
1$
#12000
b0x0x 0
b0x0x 9
b0x0x F
1&
0$
#16000
x!
1$
#20000
0$
#24000
1$
#28000
1'
0(
0$
#32000
1$
#36000
0$
#40000
1$
#44000
0'
1(
0$
#48000
1$
#52000
bx 0
bx 9
bx F
0)
0&
0$
#56000
bx 2
bx ;
bx B
bx E
bx L
1)
1$
