src/componentes.v
// Banco de registros de dos salidas y una entrada
module regfile(output wire [7:0]  RD1, RD2,     //datos leidos
               input  wire        clk,          // Señal de reloj
               input  wire        we3,          //señal de habilitación de escritura
               input  wire [3:0]  RA1, RA2, WA3,//direcciones de regs leidos y reg a escribir
               input  wire [7:0]  WD3);         //dato a escribir

  reg [7:0] R[0:15]; //memoria de 32 registros de 8 bits de ancho

  initial
  begin
    $readmemb("regfile.dat",R); // inicializa los registros a valores conocidos
  end  
  
  // El registro 0 siempre es cero
  // se leen dos reg combinacionalmente
  // y la escritura del tercero ocurre en flanco de subida del reloj
  always @(posedge clk)
    if (we3) R[WA3] <= WD3;	
  
  assign RD1 = (RA1 != 0) ? R[RA1] : 0;
  assign RD2 = (RA2 != 0) ? R[RA2] : 0;
endmodule


// Sumador simple
module sum(output wire [9:0] Y,     // Salida del sumador
           input  wire [9:0] A, B); // Operandos de la suma

  assign Y = A + B;
endmodule


// Registro de tamaño configurable para modelar el PC. Cambia en cada flanco de subida de reloj o de reset
module registro #(parameter WIDTH = 8)
              (output reg  [WIDTH-1:0] Q,           // Salida del registro
               input  wire             clk, reset,  // Señales de reloj y reseteo
               input  wire [WIDTH-1:0] D);          // Entrada al registro

  always @(posedge clk, posedge reset)
    if (reset) Q <= 0;
    else       Q <= D;
endmodule


// Multiplexor de dos entradas y una salida, de tamaño configurable. Si la señal de selección "s" vale 1, se pone el valor de d1 en la salida; d0 si vale 0
module mux2 #(parameter WIDTH = 8)
             (output wire [WIDTH-1:0] Y,      // Salida del multiplexor
              input  wire [WIDTH-1:0] D0, D1, // Entradas del multiplexor
              input  wire             s);     // Selección

  assign Y = s ? D1 : D0; 
endmodule


//Biestable para el flag de cero
//Biestable tipo D síncrono con reset asíncrono por flanco y entrada de habilitación de carga
module ffd(input wire clk, reset, d, carga, output reg q);
  always @(posedge clk, posedge reset)
    if (reset)
	    q <= 1'b0;
	  else
	    if (carga)
	      q <= d;
endmodule

src/alu.v
module alu(output reg [7:0] S, output reg zero, input wire [7:0] A, B, input wire [2:0] Op);
  always @(A, B, Op)
  begin
    case (Op)              
      3'b000: S = A; 
      3'b001: S = ~A;
      3'b010: S = A + B;
      3'b011: S = A - B;
      3'b100: S = A & B;
      3'b101: S = A | B;
      3'b110: S = -A;
      3'b111: S = -B;
      default: S = 'bx; 
    endcase
    zero = ~(|S);
  end
endmodule

src/memprog.v
module memprog(output wire [15:0] Data,     // Dato que se lee de memoria
               input  wire clk,             // Señal de reloj
               input  wire [9:0] Address);  // Dirección de memoria a la que se accede

  reg [15:0] Mem[0:1023]; //memoria de 1024 palabras de 16 bits de ancho

  initial
  begin
    $readmemb("progfile.dat", Mem); // inicializa la memoria del fichero en texto binario
  end
  assign Data = Mem[Address];
endmodule

src/microc.v
module microc(output wire [5:0] Opcode, output wire z, input wire clk, reset, s_inc, s_inm, we3, wez, input wire [2:0] Op);
//Microcontrolador sin memoria de datos de un solo ciclo

  // Inicialización
  wire [15:0] opcode;
  wire [9:0] pc_actual, pc_dir, sum_result;
  wire [7:0] reg_alu_1, reg_alu_2, wd3, alu_result;
  wire zero; 

  // Obtengo el PC
  registro PC (pc_actual, clk, reset, pc_dir);
  // Obtengo el incremento
  sum suma_pc (sum_result, pc_actual, 10'b0000000001);
  // Obtengo el opcode de la instruccion
  memprog instruccion (opcode, clk, pc_actual);
  // Elijo entre saltar a la direccion o el incremento del PC
  mux2 #(10) mux_10_bit (pc_dir, opcode[9:0], sum_result, s_inc);

  // Elijo entre el resultado de la alu y la constante inmediata
  mux2 #(8) mux_8_bit (wd3, alu_result, opcode[11:4], s_inm);
  // Hago la operacion correspondiente 
  alu ALU (alu_result, zero, reg_alu_1, reg_alu_2, Op);
  // Proceso el banco de registros
  regfile banco (reg_alu_1, reg_alu_2, clk, we3, opcode[11:8], opcode[7:4], opcode[3:0], wd3);
  // Almaceno en el ffd el zero
  ffd FFZ (clk, reset, zero, wez, z);

  // Asigno los 6 bits más significativos al Opcode
  assign Opcode = opcode[15:10];
endmodule

testbenchs/microc_tb.v
`timescale 1 ns / 10 ps
module microc_tb;

// declaración de variables
  reg test_clk, test_reset, test_s_inc, test_s_inm, test_we3, test_wez;
  reg [2:0] test_Op;
  wire [5:0] test_Opcode;
  wire test_z;
// instanciación del camino de datos
  microc camino(test_Opcode, test_z, test_clk, test_reset, test_s_inc, test_s_inm, test_we3, test_wez, test_Op);

// generación de reloj clk
  always
  begin
    test_clk = 1;
    #10;
    test_clk = 0;
    #10;
  end

// Reseteo y configuración de salidas del testbench
initial
begin
  $dumpfile("data/microc_tb.vcd");
  $dumpvars;
  // ... señal de reset
  test_reset = 1'b1;
  #5;
  test_reset = 1'b0;
end

// jmp: s_inc = 0, we3 = 1 s_inm = x, wez = 1, Op = xxx
// nop: s_inc = 1, we3 = 1, s_inm = x, wez = 1, Op = xxx
// li : s_inc = 1, we3 = 0, s_inm = 1, wez = 1, Op = xxx
// aritmetico-logicas : s_inc = 1, we3 = 1, s_inm = 0, wez = 1, Op = Sí importa pero está dentro de la alu
// jnz : s_inc = 0, we3 = 1, s_inm = x, wez = 0, Op = xxx
// jz : s_inc = 0, we3 = 1, s_inm = x, wez = 0, Op = xxx

// Bloque simulación señales control por ciclo
initial @(posedge test_clk, negedge test_reset)
begin
  #5;
  // retardos y señales para ejecutar primera instrucción (ciclo 1)
  test_s_inc = 1'b0;
  test_we3 = 1'b0;
  test_s_inm = 1'b0; // Don't care
  test_wez = 1'b0;
  test_Op = 3'b000; // Don't care
  #20;
  // retardos y señales para ejecutar primera instrucción (ciclo 1)
  test_s_inc = 1'b1;
  test_we3 = 1'b1;
  test_s_inm = 1'b1; 
  test_wez = 1'b0;
  test_Op = 3'b000; // Don't care
  #20;
  // retardos y señales para ejecutar primera instrucción (ciclo 1)
  test_s_inc = 1'b1;
  test_we3 = 1'b1;
  test_s_inm = 1'b1; 
  test_wez = 1'b0;
  test_Op = 3'b000; // Don't care
  #20;
  // retardos y señales para ejecutar primera instrucción (ciclo 1)
  test_s_inc = 1'b1;
  test_we3 = 1'b1;
  test_s_inm = 1'b1; 
  test_wez = 1'b0;
  test_Op = 3'b000; // Don't care
  #20;
  // retardos y señales para ejecutar primera instrucción (ciclo 1)
  test_s_inc = 1'b1;
  test_we3 = 1'b1;
  test_s_inm = 1'b1; 
  test_wez = 1'b0;
  test_Op = 3'b000; // Don't care
  #20;
  // retardos y señales para ejecutar primera instrucción (ciclo 1)
  test_s_inc = 1'b1;
  test_we3 = 1'b1;
  test_s_inm = 1'b0; // Don't care
  test_wez = 1'b0;
  test_Op = 3'b010; // Add
  #20;
  // retardos y señales para ejecutar primera instrucción (ciclo 1)
  test_s_inc = 1'b1;
  test_we3 = 1'b1;
  test_s_inm = 1'b0; // Don't care
  test_wez = 1'b1;
  test_Op = 3'b011; // Sub
  #20;
  // retardos y señales para ejecutar primera instrucción (ciclo 1)
  test_s_inc = 1'b0;
  test_we3 = 1'b0;
  test_s_inm = 1'b0; // Don't care
  test_wez = 1'b0;
  test_Op = 3'b000; // Don't care
  #20;
  // retardos y señales para ejecutar primera instrucción (ciclo 1)
  test_s_inc = 1'b1;
  test_we3 = 1'b1;
  test_s_inm = 1'b0; // Don't care
  test_wez = 1'b0;
  test_Op = 3'b010; // Add
  #20;
  // retardos y señales para ejecutar primera instrucción (ciclo 1)
  test_s_inc = 1'b1;
  test_we3 = 1'b1;
  test_s_inm = 1'b0; // Don't care
  test_wez = 1'b1;
  test_Op = 3'b011; // Sub
  #20;
  // retardos y señales para ejecutar primera instrucción (ciclo 1)
  test_s_inc = 1'b1;
  test_we3 = 1'b0;
  test_s_inm = 1'b0; // Don't care
  test_wez = 1'b0;
  test_Op = 3'b000; // Don't care
  #20;
  // retardos y señales para ejecutar primera instrucción (ciclo 1)
  test_s_inc = 1'b0;
  test_we3 = 1'b0;
  test_s_inm = 1'b0; // Don't care
  test_wez = 1'b0;
  test_Op = 3'b000; // Don't care
  #20;
  $finish;
end

endmodule

data/microc_tb.vcd
$date
	Sun Nov 17 19:16:06 2024
$end
$version
	Icarus Verilog
$end
$timescale
	10ps
$end
$scope module microc_tb $end
$var wire 1 ! test_z $end
$var wire 6 " test_Opcode [5:0] $end
$var reg 3 # test_Op [2:0] $end
$var reg 1 $ test_clk $end
$var reg 1 % test_reset $end
$var reg 1 & test_s_inc $end
$var reg 1 ' test_s_inm $end
$var reg 1 ( test_we3 $end
$var reg 1 ) test_wez $end
$scope module camino $end
$var wire 3 * Op [2:0] $end
$var wire 1 $ clk $end
$var wire 1 % reset $end
$var wire 1 & s_inc $end
$var wire 1 ' s_inm $end
$var wire 1 ( we3 $end
$var wire 1 ) wez $end
$var wire 1 + zero $end
$var wire 1 ! z $end
$var wire 8 , wd3 [7:0] $end
$var wire 10 - sum_result [9:0] $end
$var wire 8 . reg_alu_2 [7:0] $end
$var wire 8 / reg_alu_1 [7:0] $end
$var wire 10 0 pc_dir [9:0] $end
$var wire 10 1 pc_actual [9:0] $end
$var wire 16 2 opcode [15:0] $end
$var wire 8 3 alu_result [7:0] $end
$var wire 6 4 Opcode [5:0] $end
$scope module ALU $end
$var wire 3 5 Op [2:0] $end
$var wire 8 6 B [7:0] $end
$var wire 8 7 A [7:0] $end
$var reg 8 8 S [7:0] $end
$var reg 1 + zero $end
$upscope $end
$scope module FFZ $end
$var wire 1 ) carga $end
$var wire 1 $ clk $end
$var wire 1 + d $end
$var wire 1 % reset $end
$var reg 1 ! q $end
$upscope $end
$scope module PC $end
$var wire 1 $ clk $end
$var wire 1 % reset $end
$var wire 10 9 D [9:0] $end
$var parameter 32 : WIDTH $end
$var reg 10 ; Q [9:0] $end
$upscope $end
$scope module banco $end
$var wire 4 < RA1 [3:0] $end
$var wire 4 = RA2 [3:0] $end
$var wire 4 > WA3 [3:0] $end
$var wire 1 $ clk $end
$var wire 1 ( we3 $end
$var wire 8 ? WD3 [7:0] $end
$var wire 8 @ RD2 [7:0] $end
$var wire 8 A RD1 [7:0] $end
$upscope $end
$scope module instruccion $end
$var wire 10 B Address [9:0] $end
$var wire 16 C Data [15:0] $end
$var wire 1 $ clk $end
$upscope $end
$scope module mux_10_bit $end
$var wire 10 D D0 [9:0] $end
$var wire 1 & s $end
$var wire 10 E Y [9:0] $end
$var wire 10 F D1 [9:0] $end
$var parameter 32 G WIDTH $end
$upscope $end
$scope module mux_8_bit $end
$var wire 8 H D0 [7:0] $end
$var wire 8 I D1 [7:0] $end
$var wire 1 ' s $end
$var wire 8 J Y [7:0] $end
$var parameter 32 K WIDTH $end
$upscope $end
$scope module suma_pc $end
$var wire 10 L A [9:0] $end
$var wire 10 M B [9:0] $end
$var wire 10 N Y [9:0] $end
$upscope $end
$upscope $end
$upscope $end
$enddefinitions $end
$comment Show the parameter values. $end
$dumpall
b1000 K
b1010 G
b1010 :
$end
#0
$dumpvars
b1 N
b1 M
b0 L
bx J
b0 I
bx H
b1 F
b0x01 E
b101 D
b100000000000101 C
b0 B
b0 A
b0 @
bx ?
b101 >
b0 =
b0 <
b0 ;
b0x01 9
bx 8
b0 7
b0 6
bx 5
b10000 4
bx 3
b100000000000101 2
b0 1
b0x01 0
b0 /
b0 .
b1 -
bx ,
x+
bx *
x)
x(
x'
x&
1%
1$
bx #
b10000 "
0!
$end
#500
0%
#1000
b0 ,
b0 ?
b0 J
1+
b0 3
b0 8
b0 H
b101 0
b101 9
b101 E
b0 #
b0 *
b0 5
0)
0'
0(
0&
0$
#2000
b10 0
b10 9
b10 E
b100 "
b100 4
b10 >
b10 D
b1000000000010 2
b1000000000010 C
b110 -
b110 F
b110 N
b101 1
b101 ;
b101 B
b101 L
1$
#3000
b110 0
b110 9
b110 E
0$
1'
1(
1&
#4000
b10 ,
b10 ?
b10 J
b1 >
b10 =
b10 I
b100001 D
b111 0
b111 9
b111 E
b1000000100001 2
b1000000100001 C
b111 -
b111 F
b111 N
b110 1
b110 ;
b110 B
b110 L
1$
#5000
0$
#6000
b100 ,
b100 ?
b100 J
b11 >
b100 =
b100 I
b1000011 D
b1000 0
b1000 9
b1000 E
b1000001000011 2
b1000001000011 C
b1000 -
b1000 F
b1000 N
b111 1
b111 ;
b111 B
b111 L
1$
#7000
0$
#8000
b10 .
b10 6
b10 @
b1 ,
b1 ?
b1 J
b100 >
b1 =
b1 I
b10100 D
b1001 0
b1001 9
b1001 E
b1000000010100 2
b1000000010100 C
b1001 -
b1001 F
b1001 N
b1000 1
b1000 ;
b1000 B
b1000 L
1$
#9000
0$
#10000
b100 .
b100 6
b100 @
b100011 ,
b100011 ?
b100011 J
b101000 "
b101000 4
b10 >
b11 =
b10 <
b100011 I
b1000110010 D
b1010 0
b1010 9
b1010 E
b1010001000110010 2
b1010001000110010 C
b1010 -
b1010 F
b1010 N
b1001 1
b1001 ;
b1001 B
b1001 L
1$
#11000
0+
b100 3
b100 8
b100 H
b100 ,
b100 ?
b100 J
0$
b10 #
b10 *
b10 5
0'
#12000
b11 ,
b11 ?
b11 J
b1 .
b1 6
b1 @
b11 3
b11 8
b11 H
b101100 "
b101100 4
b1 >
b100 =
b1 <
b10100 I
b101000001 D
b1011 0
b1011 9
b1011 E
b10 /
b10 7
b10 A
b1011000101000001 2
b1011000101000001 C
b1011 -
b1011 F
b1011 N
b1010 1
b1010 ;
b1010 B
b1010 L
1$
#13000
b1 ,
b1 ?
b1 J
b1 3
b1 8
b1 H
0$
b11 #
b11 *
b11 5
1)
#14000
b0 ,
b0 ?
b0 J
b0 .
b0 6
b0 @
1+
b0 3
b0 8
b0 H
b10010 "
b10010 4
b1001 >
b0 =
b1000 <
b10000000 I
b1001 D
b1100 0
b1100 9
b1100 E
b0 /
b0 7
b0 A
b100100000001001 2
b100100000001001 C
b1100 -
b1100 F
b1100 N
b1011 1
b1011 ;
b1011 B
b1011 L
1$
#15000
b1001 0
b1001 9
b1001 E
0$
b0 #
b0 *
b0 5
0)
0(
0&
#16000
b100 ,
b100 ?
b100 J
0+
b100 3
b100 8
b100 H
b100 .
b100 6
b100 @
b100 /
b100 7
b100 A
b1000110010 0
b1000110010 9
b1000110010 E
b101000 "
b101000 4
b10 >
b11 =
b10 <
b100011 I
b1000110010 D
b1010001000110010 2
b1010001000110010 C
b1010 -
b1010 F
b1010 N
b1001 1
b1001 ;
b1001 B
b1001 L
1$
#17000
b1000 ,
b1000 ?
b1000 J
b1000 3
b1000 8
b1000 H
b1010 0
b1010 9
b1010 E
0$
b10 #
b10 *
b10 5
1(
1&
#18000
b10 ,
b10 ?
b10 J
b1 .
b1 6
b1 @
b10 3
b10 8
b10 H
b101100 "
b101100 4
b1 >
b100 =
b1 <
b10100 I
b101000001 D
b1011 0
b1011 9
b1011 E
b1 /
b1 7
b1 A
b1011000101000001 2
b1011000101000001 C
b1011 -
b1011 F
b1011 N
b1010 1
b1010 ;
b1010 B
b1010 L
1$
#19000
b0 ,
b0 ?
b0 J
1+
b0 3
b0 8
b0 H
0$
b11 #
b11 *
b11 5
1)
#20000
b0 ,
b0 ?
b0 J
b0 .
b0 6
b0 @
1+
b0 3
b0 8
b0 H
b10010 "
b10010 4
b1001 >
b0 =
b1000 <
b10000000 I
b1001 D
b1100 0
b1100 9
b1100 E
b0 /
b0 7
b0 A
b100100000001001 2
b100100000001001 C
b1100 -
b1100 F
b1100 N
b1011 1
b1011 ;
b1011 B
b1011 L
1!
1$
#21000
0$
b0 #
b0 *
b0 5
0)
0(
#22000
b10000 "
b10000 4
b1100 >
b0 <
b0 I
b1100 D
b1101 0
b1101 9
b1101 E
b100000000001100 2
b100000000001100 C
b1101 -
b1101 F
b1101 N
b1100 1
b1100 ;
b1100 B
b1100 L
1$
#23000
b1100 0
b1100 9
b1100 E
0$
0&
